{
    "client": "Thunder Client",
    "collectionName": "Reportess",
    "dateExported": "2024-01-25T19:13:48.943Z",
    "version": "1.1",
    "folders": [],
    "requests": [
        {
            "_id": "a03a55f9-3b2c-4279-877c-6985a8bced27",
            "colId": "f09f79a6-77f0-46f1-ae0b-8c4ef6e47fc9",
            "containerId": "",
            "name": "login200",
            "url": "http://localhost:8080/api/sesion",
            "method": "POST",
            "sortNum": 10000,
            "created": "2024-01-24T18:04:08.127Z",
            "modified": "2024-01-24T18:04:08.127Z",
            "headers": [],
            "params": [],
            "body": {
                "type": "json",
                "raw": "{\n  \"DNI\":\"41097334\",\n  \"contrasenia\":\"12345678\"\n}",
                "form": []
            },
            "tests": [
                {
                    "type": "res-code",
                    "custom": "",
                    "action": "equal",
                    "value": "200"
                }
            ]
        },
        {
            "_id": "2219dae1-d1ec-4afa-a3ae-219c8170722a",
            "colId": "f09f79a6-77f0-46f1-ae0b-8c4ef6e47fc9",
            "containerId": "",
            "name": "usuarioReporte404",
            "url": "http://localhost:8080/api/usuario/4/reporte",
            "method": "POST",
            "sortNum": 30000,
            "created": "2024-01-24T18:04:20.431Z",
            "modified": "2024-01-24T18:04:20.431Z",
            "headers": [],
            "params": [],
            "tests": [
                {
                    "type": "res-code",
                    "custom": "",
                    "action": "equal",
                    "value": "404"
                }
            ]
        },
        {
            "_id": "54e6025c-4e7d-49bd-9095-4fb1fd5b1873",
            "colId": "f09f79a6-77f0-46f1-ae0b-8c4ef6e47fc9",
            "containerId": "",
            "name": "usuarioReporte201",
            "url": "http://localhost:8080/api/usuario/41097335/reporte",
            "method": "POST",
            "sortNum": 40000,
            "created": "2024-01-25T17:40:47.749Z",
            "modified": "2024-01-25T17:40:47.749Z",
            "headers": [],
            "params": [],
            "tests": [
                {
                    "type": "res-code",
                    "custom": "",
                    "action": "equal",
                    "value": "201"
                }
            ]
        },
        {
            "_id": "20a2f376-2690-4596-ab14-3a22a29e27f0",
            "colId": "f09f79a6-77f0-46f1-ae0b-8c4ef6e47fc9",
            "containerId": "",
            "name": "reporteRespuesta404",
            "url": "http://localhost:8080/api/respuesta/9999999999999/reporte",
            "method": "POST",
            "sortNum": 50000,
            "created": "2024-01-25T18:36:05.910Z",
            "modified": "2024-01-25T18:36:05.910Z",
            "headers": [],
            "params": [],
            "body": {
                "type": "json",
                "raw": "{\n  \"tipo\":1\n}",
                "form": []
            },
            "tests": [
                {
                    "type": "res-code",
                    "custom": "",
                    "action": "equal",
                    "value": "404"
                }
            ]
        },
        {
            "_id": "da0ee4f4-1ed1-458e-b273-f875206adb2b",
            "colId": "f09f79a6-77f0-46f1-ae0b-8c4ef6e47fc9",
            "containerId": "",
            "name": "reportePregunta404",
            "url": "http://localhost:8080/api/pregunta/9999999999999/reporte",
            "method": "POST",
            "sortNum": 60000,
            "created": "2024-01-25T18:36:09.910Z",
            "modified": "2024-01-25T18:36:09.910Z",
            "headers": [],
            "params": [],
            "body": {
                "type": "json",
                "raw": "{\n  \"tipo\":1\n}",
                "form": []
            },
            "tests": [
                {
                    "type": "res-code",
                    "custom": "",
                    "action": "equal",
                    "value": "404"
                }
            ]
        },
        {
            "_id": "28e6f8a9-974a-4e20-b0b2-199143759a83",
            "colId": "f09f79a6-77f0-46f1-ae0b-8c4ef6e47fc9",
            "containerId": "",
            "name": "reporteRespuesta201",
            "url": "http://localhost:8080/api/respuesta/23/reporte",
            "method": "POST",
            "sortNum": 70000,
            "created": "2024-01-25T18:36:26.063Z",
            "modified": "2024-01-25T18:36:26.063Z",
            "headers": [],
            "params": [],
            "body": {
                "type": "json",
                "raw": "{\n  \"tipo\":1\n}",
                "form": []
            },
            "tests": [
                {
                    "type": "res-code",
                    "custom": "",
                    "action": "equal",
                    "value": "201"
                }
            ]
        },
        {
            "_id": "e817c739-a99e-4aff-a4a7-9283c545133d",
            "colId": "f09f79a6-77f0-46f1-ae0b-8c4ef6e47fc9",
            "containerId": "",
            "name": "reportePregunta201",
            "url": "http://localhost:8080/api/pregunta/9/reporte",
            "method": "POST",
            "sortNum": 80000,
            "created": "2024-01-25T18:36:30.215Z",
            "modified": "2024-01-25T18:36:30.215Z",
            "headers": [],
            "params": [],
            "body": {
                "type": "json",
                "raw": "{\n  \"tipo\":1\n}",
                "form": []
            },
            "tests": [
                {
                    "type": "res-code",
                    "custom": "",
                    "action": "equal",
                    "value": "201"
                }
            ]
        }
    ]
}